<annotation>
	<folder>train</folder>
	<filename>line_217875393248003.jpg</filename>
	<path>C:\Users\Hazymist\Downloads\test+train( label 5) +add 40 papercup + à¸¥à¸à¹à¸à¸¥à¹à¸ à¸²à¸ + label-20191124T023351Z-001\test+train( label 5) +add 40 papercup + ลดไฟล์ภาพ + label\train\line_217875393248003.jpg</path>
	<source>
		<database>Unknown</database>
	</source>
	<size>
		<width>2048</width>
		<height>1536</height>
		<depth>3</depth>
	</size>
	<segmented>0</segmented>
	<object>
		<name>AlCan</name>
		<pose>Unspecified</pose>
		<truncated>0</truncated>
		<difficult>0</difficult>
		<bndbox>
			<xmin>1113</xmin>
			<ymin>5</ymin>
			<xmax>1387</xmax>
			<ymax>229</ymax>
		</bndbox>
	</object>
	<object>
		<name>AlCan</name>
		<pose>Unspecified</pose>
		<truncated>0</truncated>
		<difficult>0</difficult>
		<bndbox>
			<xmin>1839</xmin>
			<ymin>10</ymin>
			<xmax>2042</xmax>
			<ymax>300</ymax>
		</bndbox>
	</object>
	<object>
		<name>AlCan</name>
		<pose>Unspecified</pose>
		<truncated>1</truncated>
		<difficult>0</difficult>
		<bndbox>
			<xmin>1763</xmin>
			<ymin>1</ymin>
			<xmax>1954</xmax>
			<ymax>103</ymax>
		</bndbox>
	</object>
	<object>
		<name>PlasticBottle</name>
		<pose>Unspecified</pose>
		<truncated>0</truncated>
		<difficult>0</difficult>
		<bndbox>
			<xmin>551</xmin>
			<ymin>438</ymin>
			<xmax>1328</xmax>
			<ymax>831</ymax>
		</bndbox>
	</object>
</annotation>
